github/__init__.py
github/__main__.py
github/context.py
github/errors.py
github/github.py
github/http.py
github/utils.py
github/abc/__init__.py
github/abc/actor.py
github/abc/assignable.py
github/abc/closable.py
github/abc/comment.py
github/abc/commentable.py
github/abc/deletable.py
github/abc/labelable.py
github/abc/lockable.py
github/abc/node.py
github/abc/participable.py
github/abc/profileowner.py
github/abc/projectowner.py
github/abc/reactable.py
github/abc/repositorynode.py
github/abc/repositoryowner.py
github/abc/subscribable.py
github/abc/type.py
github/abc/uniformresourcelocatable.py
github/abc/updatable.py
github/enums/__init__.py
github/enums/cannotupdatereason.py
github/enums/commentauthorassociation.py
github/enums/issuestate.py
github/enums/lockreason.py
github/enums/pullrequeststate.py
github/enums/reaction.py
github/enums/repositorylockreason.py
github/enums/repositorypermissions.py
github/enums/repositorysubscription.py
github/objects/__init__.py
github/objects/bot.py
github/objects/codeofconduct.py
github/objects/commitcomment.py
github/objects/issue.py
github/objects/label.py
github/objects/language.py
github/objects/license.py
github/objects/licenserule.py
github/objects/mannequin.py
github/objects/metadata.py
github/objects/organization.py
github/objects/pullrequest.py
github/objects/ratelimit.py
github/objects/reaction.py
github/objects/repository.py
github/objects/topic.py
github/objects/user.py
github/query/__init__.py
github/query/builder.py
github/query/builtin_mutations.py
github/query/builtin_queries.py
github.py-0.5.0.dist-info/LICENSE
github.py-0.5.0.dist-info/METADATA
github.py-0.5.0.dist-info/WHEEL
github.py-0.5.0.dist-info/top_level.txt
github.py-0.5.0.dist-info/RECORD
