Metadata-Version: 2.1
Name: github.py
Version: 0.5.0
Summary: An asynchronous Python wrapper for the GitHub API, v4.
Home-page: https://github.com/ShineyDev/github.py
Author: ShineyDev
License: Apache Software License
Project-URL: Documentation, https://githubpy.readthedocs.io/en/latest/
Project-URL: Issue Tracker, https://github.com/ShineyDev/github.py/issues/
Project-URL: Source, https://github.com/ShineyDev/github.py/
Platform: UNKNOWN
Classifier: Development Status :: 2 - Pre-Alpha
Classifier: Intended Audience :: Developers
Classifier: License :: OSI Approved :: Apache Software License
Classifier: Natural Language :: English
Classifier: Operating System :: OS Independent
Classifier: Programming Language :: Python :: 3 :: Only
Classifier: Programming Language :: Python :: 3.5
Classifier: Programming Language :: Python :: 3.6
Classifier: Programming Language :: Python :: 3.7
Classifier: Programming Language :: Python :: 3.8
Classifier: Topic :: Software Development
Classifier: Topic :: Software Development :: Libraries
Classifier: Topic :: Software Development :: Libraries :: Python Modules
Classifier: Topic :: Utilities
Classifier: Typing :: Typed
Requires-Python: >=3.5.2
Provides-Extra: docs
